pyscs/__init__.py
pyscs/alert.py
pyscs/alertto.py
pyscs/atom.py
pyscs/script.py
pyscs/scs.py
pyscs-3.8.4.dist-info/METADATA
pyscs-3.8.4.dist-info/WHEEL
pyscs-3.8.4.dist-info/RECORD
