Metadata-Version: 2.1
Name: pyscs
Version: 3.8.4
Summary: python lib for scs, scs version <= 3.8
Project-URL: Homepage, https://github.com/hyahm/pyscs
Project-URL: Bug Tracker, https://github.com/hyahm/pyscs/issues
Author-email: cander <cander_liubiao@126.com>
Classifier: License :: OSI Approved :: MIT License
Classifier: Operating System :: OS Independent
Classifier: Programming Language :: Python :: 3
Requires-Python: >=3.10
